<Gesture Name="p" Subject="1" Number="1" NumPts="130" Millseconds="0" AppName="Gestures" AppVer="1.0" Date="Monday, April 17, 2023" TimeOfDay="07:09:09&#10;" ID="10"><Point X="305" Y="302" T="1681740549599" /><Point X="307" Y="300" T="1681740549599" /><Point X="308" Y="298" T="1681740549599" /><Point X="309" Y="296" T="1681740549599" /><Point X="310" Y="294" T="1681740549599" /><Point X="311" Y="292" T="1681740549599" /><Point X="312" Y="290" T="1681740549599" /><Point X="312" Y="288" T="1681740549599" /><Point X="312" Y="286" T="1681740549599" /><Point X="312" Y="284" T="1681740549599" /><Point X="312" Y="282" T="1681740549599" /><Point X="312" Y="280" T="1681740549599" /><Point X="312" Y="277" T="1681740549599" /><Point X="312" Y="274" T="1681740549599" /><Point X="312" Y="271" T="1681740549599" /><Point X="312" Y="269" T="1681740549599" /><Point X="312" Y="266" T="1681740549599" /><Point X="312" Y="264" T="1681740549599" /><Point X="312" Y="262" T="1681740549599" /><Point X="311" Y="261" T="1681740549599" /><Point X="311" Y="259" T="1681740549599" /><Point X="311" Y="258" T="1681740549599" /><Point X="311" Y="257" T="1681740549599" /><Point X="311" Y="256" T="1681740549599" /><Point X="311" Y="257" T="1681740549599" /><Point X="311" Y="259" T="1681740549599" /><Point X="311" Y="260" T="1681740549599" /><Point X="312" Y="263" T="1681740549599" /><Point X="312" Y="266" T="1681740549599" /><Point X="312" Y="269" T="1681740549599" /><Point X="312" Y="272" T="1681740549599" /><Point X="312" Y="276" T="1681740549599" /><Point X="313" Y="280" T="1681740549599" /><Point X="313" Y="283" T="1681740549599" /><Point X="314" Y="287" T="1681740549599" /><Point X="314" Y="291" T="1681740549599" /><Point X="315" Y="295" T="1681740549599" /><Point X="316" Y="299" T="1681740549599" /><Point X="316" Y="303" T="1681740549599" /><Point X="317" Y="307" T="1681740549599" /><Point X="318" Y="312" T="1681740549599" /><Point X="319" Y="317" T="1681740549599" /><Point X="320" Y="320" T="1681740549599" /><Point X="320" Y="324" T="1681740549599" /><Point X="321" Y="328" T="1681740549599" /><Point X="321" Y="332" T="1681740549599" /><Point X="322" Y="337" T="1681740549599" /><Point X="322" Y="340" T="1681740549599" /><Point X="322" Y="343" T="1681740549599" /><Point X="322" Y="345" T="1681740549599" /><Point X="321" Y="347" T="1681740549599" /><Point X="321" Y="350" T="1681740549599" /><Point X="321" Y="352" T="1681740549599" /><Point X="321" Y="353" T="1681740549599" /><Point X="321" Y="354" T="1681740549599" /><Point X="321" Y="355" T="1681740549599" /><Point X="320" Y="355" T="1681740549599" /><Point X="320" Y="354" T="1681740549599" /><Point X="319" Y="354" T="1681740549599" /><Point X="318" Y="353" T="1681740549599" /><Point X="318" Y="352" T="1681740549599" /><Point X="317" Y="351" T="1681740549599" /><Point X="316" Y="349" T="1681740549599" /><Point X="315" Y="346" T="1681740549599" /><Point X="314" Y="343" T="1681740549599" /><Point X="314" Y="341" T="1681740549599" /><Point X="313" Y="338" T="1681740549599" /><Point X="313" Y="335" T="1681740549599" /><Point X="313" Y="333" T="1681740549599" /><Point X="313" Y="331" T="1681740549599" /><Point X="313" Y="329" T="1681740549599" /><Point X="313" Y="325" T="1681740549599" /><Point X="312" Y="321" T="1681740549599" /><Point X="312" Y="317" T="1681740549599" /><Point X="312" Y="313" T="1681740549599" /><Point X="312" Y="310" T="1681740549599" /><Point X="313" Y="307" T="1681740549599" /><Point X="313" Y="305" T="1681740549599" /><Point X="313" Y="302" T="1681740549599" /><Point X="314" Y="299" T="1681740549599" /><Point X="314" Y="297" T="1681740549599" /><Point X="315" Y="294" T="1681740549599" /><Point X="316" Y="292" T="1681740549599" /><Point X="316" Y="290" T="1681740549599" /><Point X="317" Y="288" T="1681740549599" /><Point X="318" Y="286" T="1681740549599" /><Point X="319" Y="284" T="1681740549599" /><Point X="320" Y="283" T="1681740549599" /><Point X="321" Y="282" T="1681740549599" /><Point X="323" Y="281" T="1681740549599" /><Point X="325" Y="280" T="1681740549599" /><Point X="326" Y="279" T="1681740549599" /><Point X="328" Y="279" T="1681740549599" /><Point X="329" Y="278" T="1681740549599" /><Point X="330" Y="278" T="1681740549599" /><Point X="332" Y="277" T="1681740549599" /><Point X="334" Y="277" T="1681740549599" /><Point X="336" Y="277" T="1681740549599" /><Point X="337" Y="277" T="1681740549599" /><Point X="339" Y="277" T="1681740549599" /><Point X="341" Y="277" T="1681740549599" /><Point X="342" Y="277" T="1681740549599" /><Point X="344" Y="278" T="1681740549599" /><Point X="345" Y="278" T="1681740549599" /><Point X="347" Y="279" T="1681740549599" /><Point X="349" Y="279" T="1681740549599" /><Point X="350" Y="281" T="1681740549599" /><Point X="352" Y="282" T="1681740549599" /><Point X="353" Y="283" T="1681740549599" /><Point X="354" Y="285" T="1681740549599" /><Point X="355" Y="286" T="1681740549599" /><Point X="356" Y="288" T="1681740549599" /><Point X="356" Y="290" T="1681740549599" /><Point X="356" Y="291" T="1681740549599" /><Point X="356" Y="294" T="1681740549599" /><Point X="355" Y="295" T="1681740549599" /><Point X="354" Y="298" T="1681740549599" /><Point X="352" Y="301" T="1681740549599" /><Point X="349" Y="303" T="1681740549599" /><Point X="346" Y="305" T="1681740549599" /><Point X="344" Y="306" T="1681740549599" /><Point X="343" Y="307" T="1681740549599" /><Point X="341" Y="308" T="1681740549599" /><Point X="340" Y="309" T="1681740549599" /><Point X="337" Y="310" T="1681740549599" /><Point X="335" Y="310" T="1681740549599" /><Point X="333" Y="310" T="1681740549599" /><Point X="329" Y="309" T="1681740549599" /><Point X="327" Y="309" T="1681740549599" /><Point X="326" Y="308" T="1681740549599" /></Gesture>