<Gesture Name="u" Subject="1" Number="1" NumPts="130" Millseconds="0" AppName="Gestures" AppVer="1.0" Date="Monday, April 17, 2023" TimeOfDay="05:38:52&#10;" ID="5"><Point X="222" Y="347" T="1681735132369" /><Point X="227" Y="341" T="1681735132369" /><Point X="229" Y="337" T="1681735132369" /><Point X="230" Y="334" T="1681735132369" /><Point X="232" Y="331" T="1681735132369" /><Point X="234" Y="329" T="1681735132369" /><Point X="237" Y="326" T="1681735132369" /><Point X="240" Y="321" T="1681735132369" /><Point X="242" Y="316" T="1681735132369" /><Point X="244" Y="311" T="1681735132369" /><Point X="246" Y="309" T="1681735132369" /><Point X="247" Y="306" T="1681735132369" /><Point X="248" Y="303" T="1681735132369" /><Point X="250" Y="299" T="1681735132369" /><Point X="252" Y="295" T="1681735132369" /><Point X="253" Y="291" T="1681735132369" /><Point X="253" Y="287" T="1681735132369" /><Point X="254" Y="285" T="1681735132369" /><Point X="254" Y="283" T="1681735132369" /><Point X="255" Y="281" T="1681735132369" /><Point X="256" Y="279" T="1681735132369" /><Point X="256" Y="277" T="1681735132369" /><Point X="257" Y="274" T="1681735132369" /><Point X="257" Y="272" T="1681735132369" /><Point X="257" Y="270" T="1681735132369" /><Point X="258" Y="267" T="1681735132369" /><Point X="258" Y="265" T="1681735132369" /><Point X="258" Y="263" T="1681735132369" /><Point X="258" Y="262" T="1681735132369" /><Point X="258" Y="261" T="1681735132369" /><Point X="258" Y="260" T="1681735132369" /><Point X="258" Y="259" T="1681735132369" /><Point X="258" Y="260" T="1681735132369" /><Point X="257" Y="261" T="1681735132369" /><Point X="257" Y="262" T="1681735132369" /><Point X="256" Y="263" T="1681735132369" /><Point X="254" Y="266" T="1681735132369" /><Point X="253" Y="269" T="1681735132369" /><Point X="253" Y="271" T="1681735132369" /><Point X="251" Y="277" T="1681735132369" /><Point X="249" Y="283" T="1681735132369" /><Point X="247" Y="287" T="1681735132369" /><Point X="244" Y="292" T="1681735132369" /><Point X="241" Y="297" T="1681735132369" /><Point X="238" Y="304" T="1681735132369" /><Point X="237" Y="310" T="1681735132369" /><Point X="236" Y="314" T="1681735132369" /><Point X="235" Y="318" T="1681735132369" /><Point X="234" Y="323" T="1681735132369" /><Point X="234" Y="329" T="1681735132369" /><Point X="233" Y="333" T="1681735132369" /><Point X="233" Y="336" T="1681735132369" /><Point X="234" Y="339" T="1681735132369" /><Point X="234" Y="341" T="1681735132369" /><Point X="235" Y="343" T="1681735132369" /><Point X="236" Y="345" T="1681735132369" /><Point X="237" Y="346" T="1681735132369" /><Point X="239" Y="347" T="1681735132369" /><Point X="241" Y="349" T="1681735132369" /><Point X="242" Y="350" T="1681735132369" /><Point X="244" Y="351" T="1681735132369" /><Point X="246" Y="351" T="1681735132369" /><Point X="248" Y="352" T="1681735132369" /><Point X="249" Y="352" T="1681735132369" /><Point X="251" Y="352" T="1681735132369" /><Point X="253" Y="352" T="1681735132369" /><Point X="257" Y="351" T="1681735132369" /><Point X="261" Y="350" T="1681735132369" /><Point X="264" Y="349" T="1681735132369" /><Point X="268" Y="347" T="1681735132369" /><Point X="270" Y="345" T="1681735132369" /><Point X="273" Y="342" T="1681735132369" /><Point X="276" Y="339" T="1681735132369" /><Point X="278" Y="336" T="1681735132369" /><Point X="280" Y="334" T="1681735132369" /><Point X="281" Y="331" T="1681735132369" /><Point X="283" Y="330" T="1681735132369" /><Point X="284" Y="327" T="1681735132369" /><Point X="286" Y="325" T="1681735132369" /><Point X="288" Y="322" T="1681735132369" /><Point X="289" Y="318" T="1681735132369" /><Point X="291" Y="315" T="1681735132369" /><Point X="292" Y="311" T="1681735132369" /><Point X="293" Y="308" T="1681735132369" /><Point X="294" Y="306" T="1681735132369" /><Point X="296" Y="305" T="1681735132369" /><Point X="296" Y="303" T="1681735132369" /><Point X="297" Y="302" T="1681735132369" /><Point X="298" Y="299" T="1681735132369" /><Point X="298" Y="296" T="1681735132369" /><Point X="299" Y="293" T="1681735132369" /><Point X="300" Y="290" T="1681735132369" /><Point X="300" Y="287" T="1681735132369" /><Point X="300" Y="285" T="1681735132369" /><Point X="300" Y="283" T="1681735132369" /><Point X="300" Y="282" T="1681735132369" /><Point X="300" Y="281" T="1681735132369" /><Point X="300" Y="280" T="1681735132369" /><Point X="300" Y="279" T="1681735132369" /><Point X="300" Y="278" T="1681735132369" /><Point X="300" Y="277" T="1681735132369" /><Point X="300" Y="278" T="1681735132369" /><Point X="301" Y="280" T="1681735132369" /><Point X="301" Y="283" T="1681735132369" /><Point X="301" Y="286" T="1681735132369" /><Point X="301" Y="289" T="1681735132369" /><Point X="301" Y="292" T="1681735132369" /><Point X="301" Y="295" T="1681735132369" /><Point X="301" Y="301" T="1681735132369" /><Point X="301" Y="306" T="1681735132369" /><Point X="301" Y="311" T="1681735132369" /><Point X="301" Y="314" T="1681735132369" /><Point X="301" Y="318" T="1681735132369" /><Point X="301" Y="320" T="1681735132369" /><Point X="302" Y="324" T="1681735132369" /><Point X="303" Y="329" T="1681735132369" /><Point X="304" Y="332" T="1681735132369" /><Point X="305" Y="335" T="1681735132369" /><Point X="306" Y="338" T="1681735132369" /><Point X="306" Y="340" T="1681735132369" /><Point X="307" Y="341" T="1681735132369" /><Point X="308" Y="342" T="1681735132369" /><Point X="309" Y="343" T="1681735132369" /><Point X="310" Y="344" T="1681735132369" /><Point X="312" Y="345" T="1681735132369" /><Point X="313" Y="345" T="1681735132369" /><Point X="314" Y="346" T="1681735132369" /><Point X="316" Y="346" T="1681735132369" /><Point X="317" Y="346" T="1681735132369" /><Point X="318" Y="345" T="1681735132369" /></Gesture>