<Gesture Name="caret" Subject="1" Number="1" NumPts="68" Millseconds="0" AppName="Gestures" AppVer="1.0" Date="Wednesday, March 08, 2023" TimeOfDay="16:47:59&#10;" ID="5"><Point X="173" Y="289" T="1678312079696" /><Point X="178" Y="284" T="1678312079696" /><Point X="184" Y="277" T="1678312079696" /><Point X="188" Y="273" T="1678312079696" /><Point X="192" Y="265" T="1678312079696" /><Point X="196" Y="260" T="1678312079696" /><Point X="197" Y="255" T="1678312079696" /><Point X="199" Y="248" T="1678312079696" /><Point X="201" Y="242" T="1678312079696" /><Point X="204" Y="237" T="1678312079696" /><Point X="206" Y="233" T="1678312079696" /><Point X="208" Y="229" T="1678312079696" /><Point X="210" Y="224" T="1678312079696" /><Point X="213" Y="219" T="1678312079696" /><Point X="214" Y="217" T="1678312079696" /><Point X="215" Y="217" T="1678312079696" /><Point X="215" Y="216" T="1678312079696" /><Point X="216" Y="215" T="1678312079696" /><Point X="216" Y="214" T="1678312079696" /><Point X="218" Y="216" T="1678312079696" /><Point X="219" Y="221" T="1678312079696" /><Point X="220" Y="223" T="1678312079696" /><Point X="220" Y="225" T="1678312079696" /><Point X="221" Y="228" T="1678312079696" /><Point X="223" Y="230" T="1678312079696" /><Point X="224" Y="232" T="1678312079696" /><Point X="224" Y="233" T="1678312079696" /><Point X="225" Y="236" T="1678312079696" /><Point X="227" Y="238" T="1678312079696" /><Point X="228" Y="241" T="1678312079696" /><Point X="231" Y="246" T="1678312079696" /><Point X="232" Y="249" T="1678312079696" /><Point X="235" Y="254" T="1678312079696" /><Point X="236" Y="257" T="1678312079696" /><Point X="236" Y="260" T="1678312079696" /><Point X="236" Y="262" T="1678312079696" /><Point X="237" Y="264" T="1678312079696" /><Point X="239" Y="265" T="1678312079696" /><Point X="240" Y="267" T="1678312079696" /><Point X="240" Y="269" T="1678312079696" /><Point X="242" Y="270" T="1678312079696" /><Point X="242" Y="271" T="1678312079696" /><Point X="244" Y="273" T="1678312079696" /><Point X="245" Y="275" T="1678312079696" /><Point X="247" Y="277" T="1678312079696" /><Point X="248" Y="277" T="1678312079696" /><Point X="248" Y="279" T="1678312079696" /><Point X="248" Y="280" T="1678312079696" /><Point X="249" Y="281" T="1678312079696" /><Point X="250" Y="281" T="1678312079696" /><Point X="251" Y="282" T="1678312079696" /><Point X="251" Y="283" T="1678312079696" /><Point X="252" Y="283" T="1678312079696" /><Point X="252" Y="284" T="1678312079696" /><Point X="253" Y="285" T="1678312079696" /><Point X="254" Y="287" T="1678312079696" /><Point X="255" Y="287" T="1678312079696" /><Point X="255" Y="289" T="1678312079696" /><Point X="255" Y="290" T="1678312079696" /><Point X="256" Y="291" T="1678312079696" /><Point X="256" Y="293" T="1678312079696" /><Point X="257" Y="294" T="1678312079696" /><Point X="257" Y="295" T="1678312079696" /><Point X="257" Y="296" T="1678312079696" /><Point X="257" Y="297" T="1678312079696" /><Point X="257" Y="298" T="1678312079696" /><Point X="257" Y="299" T="1678312079696" /><Point X="257" Y="300" T="1678312079696" /></Gesture>