<Gesture Name="left-curly-brace" Subject="1" Number="1" NumPts="139" Millseconds="0" AppName="Gestures" AppVer="1.0" Date="Wednesday, March 08, 2023" TimeOfDay="16:49:55&#10;" ID="6"><Point X="197" Y="143" T="1678312195565" /><Point X="196" Y="143" T="1678312195565" /><Point X="193" Y="142" T="1678312195565" /><Point X="192" Y="142" T="1678312195565" /><Point X="190" Y="142" T="1678312195565" /><Point X="189" Y="142" T="1678312195565" /><Point X="188" Y="142" T="1678312195565" /><Point X="187" Y="142" T="1678312195565" /><Point X="185" Y="142" T="1678312195565" /><Point X="184" Y="143" T="1678312195565" /><Point X="184" Y="144" T="1678312195565" /><Point X="183" Y="145" T="1678312195565" /><Point X="181" Y="146" T="1678312195565" /><Point X="178" Y="149" T="1678312195565" /><Point X="176" Y="152" T="1678312195565" /><Point X="173" Y="154" T="1678312195565" /><Point X="171" Y="157" T="1678312195565" /><Point X="168" Y="161" T="1678312195565" /><Point X="166" Y="162" T="1678312195565" /><Point X="164" Y="165" T="1678312195565" /><Point X="164" Y="167" T="1678312195565" /><Point X="163" Y="169" T="1678312195565" /><Point X="161" Y="170" T="1678312195565" /><Point X="160" Y="171" T="1678312195565" /><Point X="160" Y="174" T="1678312195565" /><Point X="160" Y="177" T="1678312195565" /><Point X="159" Y="179" T="1678312195565" /><Point X="159" Y="183" T="1678312195565" /><Point X="159" Y="185" T="1678312195565" /><Point X="159" Y="189" T="1678312195565" /><Point X="159" Y="191" T="1678312195565" /><Point X="159" Y="193" T="1678312195565" /><Point X="159" Y="196" T="1678312195565" /><Point X="159" Y="198" T="1678312195565" /><Point X="159" Y="201" T="1678312195565" /><Point X="160" Y="203" T="1678312195565" /><Point X="160" Y="205" T="1678312195565" /><Point X="163" Y="208" T="1678312195565" /><Point X="164" Y="213" T="1678312195565" /><Point X="168" Y="216" T="1678312195565" /><Point X="171" Y="220" T="1678312195565" /><Point X="174" Y="224" T="1678312195565" /><Point X="176" Y="228" T="1678312195565" /><Point X="177" Y="232" T="1678312195565" /><Point X="179" Y="234" T="1678312195565" /><Point X="181" Y="237" T="1678312195565" /><Point X="182" Y="240" T="1678312195565" /><Point X="183" Y="241" T="1678312195565" /><Point X="183" Y="242" T="1678312195565" /><Point X="184" Y="245" T="1678312195565" /><Point X="184" Y="248" T="1678312195565" /><Point X="185" Y="249" T="1678312195565" /><Point X="185" Y="251" T="1678312195565" /><Point X="185" Y="253" T="1678312195565" /><Point X="185" Y="254" T="1678312195565" /><Point X="185" Y="256" T="1678312195565" /><Point X="185" Y="257" T="1678312195565" /><Point X="185" Y="259" T="1678312195565" /><Point X="185" Y="261" T="1678312195565" /><Point X="184" Y="263" T="1678312195565" /><Point X="184" Y="265" T="1678312195565" /><Point X="180" Y="269" T="1678312195565" /><Point X="177" Y="272" T="1678312195565" /><Point X="175" Y="275" T="1678312195565" /><Point X="172" Y="277" T="1678312195565" /><Point X="169" Y="278" T="1678312195565" /><Point X="168" Y="280" T="1678312195565" /><Point X="166" Y="281" T="1678312195565" /><Point X="165" Y="282" T="1678312195565" /><Point X="164" Y="283" T="1678312195565" /><Point X="164" Y="284" T="1678312195565" /><Point X="163" Y="284" T="1678312195565" /><Point X="162" Y="284" T="1678312195565" /><Point X="161" Y="284" T="1678312195565" /><Point X="161" Y="283" T="1678312195565" /><Point X="161" Y="282" T="1678312195565" /><Point X="161" Y="281" T="1678312195565" /><Point X="162" Y="281" T="1678312195565" /><Point X="163" Y="281" T="1678312195565" /><Point X="164" Y="282" T="1678312195565" /><Point X="166" Y="283" T="1678312195565" /><Point X="168" Y="284" T="1678312195565" /><Point X="168" Y="285" T="1678312195565" /><Point X="171" Y="287" T="1678312195565" /><Point X="172" Y="290" T="1678312195565" /><Point X="174" Y="293" T="1678312195565" /><Point X="176" Y="299" T="1678312195565" /><Point X="178" Y="304" T="1678312195565" /><Point X="181" Y="309" T="1678312195565" /><Point X="182" Y="314" T="1678312195565" /><Point X="183" Y="318" T="1678312195565" /><Point X="184" Y="321" T="1678312195565" /><Point X="184" Y="324" T="1678312195565" /><Point X="184" Y="326" T="1678312195565" /><Point X="184" Y="329" T="1678312195565" /><Point X="184" Y="331" T="1678312195565" /><Point X="184" Y="335" T="1678312195565" /><Point X="183" Y="338" T="1678312195565" /><Point X="182" Y="342" T="1678312195565" /><Point X="179" Y="347" T="1678312195565" /><Point X="177" Y="354" T="1678312195565" /><Point X="175" Y="361" T="1678312195565" /><Point X="173" Y="365" T="1678312195565" /><Point X="172" Y="370" T="1678312195565" /><Point X="168" Y="375" T="1678312195565" /><Point X="168" Y="381" T="1678312195565" /><Point X="167" Y="387" T="1678312195565" /><Point X="164" Y="397" T="1678312195565" /><Point X="164" Y="405" T="1678312195565" /><Point X="162" Y="412" T="1678312195565" /><Point X="162" Y="417" T="1678312195565" /><Point X="162" Y="422" T="1678312195565" /><Point X="162" Y="427" T="1678312195565" /><Point X="162" Y="432" T="1678312195565" /><Point X="162" Y="439" T="1678312195565" /><Point X="162" Y="443" T="1678312195565" /><Point X="163" Y="449" T="1678312195565" /><Point X="164" Y="453" T="1678312195565" /><Point X="164" Y="457" T="1678312195565" /><Point X="165" Y="461" T="1678312195565" /><Point X="166" Y="464" T="1678312195565" /><Point X="167" Y="465" T="1678312195565" /><Point X="168" Y="467" T="1678312195565" /><Point X="168" Y="469" T="1678312195565" /><Point X="170" Y="471" T="1678312195565" /><Point X="172" Y="473" T="1678312195565" /><Point X="174" Y="474" T="1678312195565" /><Point X="177" Y="475" T="1678312195565" /><Point X="180" Y="475" T="1678312195565" /><Point X="181" Y="476" T="1678312195565" /><Point X="185" Y="476" T="1678312195565" /><Point X="188" Y="476" T="1678312195565" /><Point X="190" Y="476" T="1678312195565" /><Point X="192" Y="476" T="1678312195565" /><Point X="195" Y="476" T="1678312195565" /><Point X="196" Y="476" T="1678312195565" /><Point X="197" Y="476" T="1678312195565" /><Point X="198" Y="476" T="1678312195565" /><Point X="199" Y="476" T="1678312195565" /></Gesture>