<Gesture Name="star" Subject="1" Number="1" NumPts="246" Millseconds="0" AppName="Gestures" AppVer="1.0" Date="Wednesday, March 08, 2023" TimeOfDay="16:54:06&#10;" ID="9"><Point X="169" Y="301" T="1678312446158" /><Point X="181" Y="287" T="1678312446158" /><Point X="203" Y="252" T="1678312446158" /><Point X="221" Y="217" T="1678312446158" /><Point X="231" Y="201" T="1678312446158" /><Point X="236" Y="190" T="1678312446158" /><Point X="247" Y="173" T="1678312446158" /><Point X="257" Y="153" T="1678312446158" /><Point X="263" Y="141" T="1678312446158" /><Point X="268" Y="132" T="1678312446158" /><Point X="271" Y="127" T="1678312446158" /><Point X="274" Y="120" T="1678312446158" /><Point X="278" Y="112" T="1678312446158" /><Point X="281" Y="103" T="1678312446158" /><Point X="284" Y="93" T="1678312446158" /><Point X="288" Y="85" T="1678312446158" /><Point X="292" Y="77" T="1678312446158" /><Point X="293" Y="73" T="1678312446158" /><Point X="296" Y="69" T="1678312446158" /><Point X="297" Y="65" T="1678312446158" /><Point X="298" Y="62" T="1678312446158" /><Point X="299" Y="60" T="1678312446158" /><Point X="300" Y="58" T="1678312446158" /><Point X="300" Y="55" T="1678312446158" /><Point X="301" Y="53" T="1678312446158" /><Point X="302" Y="53" T="1678312446158" /><Point X="304" Y="53" T="1678312446158" /><Point X="304" Y="52" T="1678312446158" /><Point X="304" Y="51" T="1678312446158" /><Point X="304" Y="50" T="1678312446158" /><Point X="304" Y="51" T="1678312446158" /><Point X="304" Y="52" T="1678312446158" /><Point X="305" Y="52" T="1678312446158" /><Point X="305" Y="53" T="1678312446158" /><Point X="306" Y="54" T="1678312446158" /><Point X="308" Y="56" T="1678312446158" /><Point X="310" Y="57" T="1678312446158" /><Point X="312" Y="60" T="1678312446158" /><Point X="314" Y="65" T="1678312446158" /><Point X="320" Y="73" T="1678312446158" /><Point X="324" Y="82" T="1678312446158" /><Point X="327" Y="91" T="1678312446158" /><Point X="331" Y="98" T="1678312446158" /><Point X="336" Y="108" T="1678312446158" /><Point X="341" Y="122" T="1678312446158" /><Point X="346" Y="138" T="1678312446158" /><Point X="351" Y="151" T="1678312446158" /><Point X="356" Y="161" T="1678312446158" /><Point X="362" Y="173" T="1678312446158" /><Point X="371" Y="189" T="1678312446158" /><Point X="379" Y="205" T="1678312446158" /><Point X="383" Y="216" T="1678312446158" /><Point X="387" Y="223" T="1678312446158" /><Point X="392" Y="232" T="1678312446158" /><Point X="396" Y="239" T="1678312446158" /><Point X="400" Y="246" T="1678312446158" /><Point X="404" Y="253" T="1678312446158" /><Point X="405" Y="257" T="1678312446158" /><Point X="406" Y="259" T="1678312446158" /><Point X="407" Y="261" T="1678312446158" /><Point X="407" Y="263" T="1678312446158" /><Point X="407" Y="264" T="1678312446158" /><Point X="407" Y="265" T="1678312446158" /><Point X="407" Y="266" T="1678312446158" /><Point X="407" Y="267" T="1678312446158" /><Point X="407" Y="268" T="1678312446158" /><Point X="407" Y="269" T="1678312446158" /><Point X="405" Y="267" T="1678312446158" /><Point X="398" Y="262" T="1678312446158" /><Point X="381" Y="252" T="1678312446158" /><Point X="365" Y="242" T="1678312446158" /><Point X="345" Y="235" T="1678312446158" /><Point X="315" Y="223" T="1678312446158" /><Point X="292" Y="213" T="1678312446158" /><Point X="271" Y="201" T="1678312446158" /><Point X="241" Y="185" T="1678312446158" /><Point X="221" Y="175" T="1678312446158" /><Point X="210" Y="170" T="1678312446158" /><Point X="200" Y="165" T="1678312446158" /><Point X="193" Y="161" T="1678312446158" /><Point X="187" Y="160" T="1678312446158" /><Point X="180" Y="157" T="1678312446158" /><Point X="176" Y="156" T="1678312446158" /><Point X="172" Y="155" T="1678312446158" /><Point X="168" Y="154" T="1678312446158" /><Point X="165" Y="153" T="1678312446158" /><Point X="164" Y="153" T="1678312446158" /><Point X="162" Y="153" T="1678312446158" /><Point X="161" Y="153" T="1678312446158" /><Point X="160" Y="153" T="1678312446158" /><Point X="159" Y="153" T="1678312446158" /><Point X="158" Y="153" T="1678312446158" /><Point X="157" Y="153" T="1678312446158" /><Point X="158" Y="152" T="1678312446158" /><Point X="164" Y="151" T="1678312446158" /><Point X="174" Y="150" T="1678312446158" /><Point X="186" Y="147" T="1678312446158" /><Point X="203" Y="145" T="1678312446158" /><Point X="226" Y="141" T="1678312446158" /><Point X="238" Y="141" T="1678312446158" /><Point X="250" Y="138" T="1678312446158" /><Point X="263" Y="136" T="1678312446158" /><Point X="273" Y="134" T="1678312446158" /><Point X="283" Y="133" T="1678312446158" /><Point X="291" Y="132" T="1678312446158" /><Point X="296" Y="130" T="1678312446158" /><Point X="303" Y="128" T="1678312446158" /><Point X="309" Y="125" T="1678312446158" /><Point X="316" Y="122" T="1678312446158" /><Point X="326" Y="119" T="1678312446158" /><Point X="335" Y="117" T="1678312446158" /><Point X="342" Y="113" T="1678312446158" /><Point X="346" Y="112" T="1678312446158" /><Point X="351" Y="111" T="1678312446158" /><Point X="353" Y="110" T="1678312446158" /><Point X="355" Y="109" T="1678312446158" /><Point X="358" Y="109" T="1678312446158" /><Point X="360" Y="109" T="1678312446158" /><Point X="364" Y="109" T="1678312446158" /><Point X="368" Y="108" T="1678312446158" /><Point X="371" Y="108" T="1678312446158" /><Point X="375" Y="108" T="1678312446158" /><Point X="378" Y="106" T="1678312446158" /><Point X="382" Y="106" T="1678312446158" /><Point X="385" Y="106" T="1678312446158" /><Point X="387" Y="106" T="1678312446158" /><Point X="390" Y="106" T="1678312446158" /><Point X="392" Y="106" T="1678312446158" /><Point X="393" Y="106" T="1678312446158" /><Point X="394" Y="106" T="1678312446158" /><Point X="396" Y="106" T="1678312446158" /><Point X="397" Y="106" T="1678312446158" /><Point X="398" Y="106" T="1678312446158" /><Point X="400" Y="106" T="1678312446158" /><Point X="401" Y="105" T="1678312446158" /><Point X="404" Y="105" T="1678312446158" /><Point X="406" Y="105" T="1678312446158" /><Point X="408" Y="105" T="1678312446158" /><Point X="410" Y="105" T="1678312446158" /><Point X="412" Y="105" T="1678312446158" /><Point X="413" Y="105" T="1678312446158" /><Point X="414" Y="105" T="1678312446158" /><Point X="414" Y="106" T="1678312446158" /><Point X="413" Y="107" T="1678312446158" /><Point X="413" Y="108" T="1678312446158" /><Point X="412" Y="108" T="1678312446158" /><Point X="411" Y="109" T="1678312446158" /><Point X="408" Y="110" T="1678312446158" /><Point X="406" Y="113" T="1678312446158" /><Point X="403" Y="117" T="1678312446158" /><Point X="396" Y="121" T="1678312446158" /><Point X="387" Y="126" T="1678312446158" /><Point X="380" Y="130" T="1678312446158" /><Point X="373" Y="134" T="1678312446158" /><Point X="366" Y="137" T="1678312446158" /><Point X="362" Y="139" T="1678312446158" /><Point X="357" Y="141" T="1678312446158" /><Point X="352" Y="145" T="1678312446158" /><Point X="348" Y="146" T="1678312446158" /><Point X="344" Y="148" T="1678312446158" /><Point X="339" Y="151" T="1678312446158" /><Point X="335" Y="154" T="1678312446158" /><Point X="331" Y="157" T="1678312446158" /><Point X="327" Y="160" T="1678312446158" /><Point X="322" Y="165" T="1678312446158" /><Point X="319" Y="168" T="1678312446158" /><Point X="315" Y="173" T="1678312446158" /><Point X="309" Y="177" T="1678312446158" /><Point X="306" Y="181" T="1678312446158" /><Point X="303" Y="183" T="1678312446158" /><Point X="300" Y="185" T="1678312446158" /><Point X="297" Y="189" T="1678312446158" /><Point X="292" Y="192" T="1678312446158" /><Point X="288" Y="195" T="1678312446158" /><Point X="284" Y="200" T="1678312446158" /><Point X="280" Y="203" T="1678312446158" /><Point X="276" Y="208" T="1678312446158" /><Point X="272" Y="212" T="1678312446158" /><Point X="269" Y="215" T="1678312446158" /><Point X="267" Y="219" T="1678312446158" /><Point X="264" Y="222" T="1678312446158" /><Point X="261" Y="225" T="1678312446158" /><Point X="259" Y="227" T="1678312446158" /><Point X="258" Y="229" T="1678312446158" /><Point X="256" Y="230" T="1678312446158" /><Point X="255" Y="231" T="1678312446158" /><Point X="253" Y="233" T="1678312446158" /><Point X="251" Y="234" T="1678312446158" /><Point X="250" Y="236" T="1678312446158" /><Point X="248" Y="237" T="1678312446158" /><Point X="247" Y="238" T="1678312446158" /><Point X="244" Y="241" T="1678312446158" /><Point X="241" Y="243" T="1678312446158" /><Point X="240" Y="245" T="1678312446158" /><Point X="236" Y="248" T="1678312446158" /><Point X="234" Y="252" T="1678312446158" /><Point X="232" Y="254" T="1678312446158" /><Point X="230" Y="258" T="1678312446158" /><Point X="226" Y="261" T="1678312446158" /><Point X="224" Y="265" T="1678312446158" /><Point X="221" Y="268" T="1678312446158" /><Point X="218" Y="270" T="1678312446158" /><Point X="216" Y="273" T="1678312446158" /><Point X="215" Y="275" T="1678312446158" /><Point X="210" Y="277" T="1678312446158" /><Point X="208" Y="281" T="1678312446158" /><Point X="205" Y="282" T="1678312446158" /><Point X="204" Y="284" T="1678312446158" /><Point X="199" Y="286" T="1678312446158" /><Point X="196" Y="288" T="1678312446158" /><Point X="196" Y="289" T="1678312446158" /><Point X="193" Y="290" T="1678312446158" /><Point X="191" Y="292" T="1678312446158" /><Point X="188" Y="293" T="1678312446158" /><Point X="186" Y="295" T="1678312446158" /><Point X="184" Y="297" T="1678312446158" /><Point X="183" Y="300" T="1678312446158" /><Point X="181" Y="301" T="1678312446158" /><Point X="181" Y="302" T="1678312446158" /><Point X="180" Y="304" T="1678312446158" /><Point X="179" Y="305" T="1678312446158" /><Point X="178" Y="305" T="1678312446158" /><Point X="177" Y="306" T="1678312446158" /><Point X="176" Y="306" T="1678312446158" /><Point X="176" Y="308" T="1678312446158" /><Point X="176" Y="310" T="1678312446158" /><Point X="175" Y="310" T="1678312446158" /><Point X="174" Y="312" T="1678312446158" /><Point X="172" Y="313" T="1678312446158" /><Point X="172" Y="314" T="1678312446158" /><Point X="172" Y="315" T="1678312446158" /><Point X="171" Y="317" T="1678312446158" /><Point X="170" Y="317" T="1678312446158" /><Point X="168" Y="318" T="1678312446158" /><Point X="168" Y="319" T="1678312446158" /><Point X="167" Y="320" T="1678312446158" /><Point X="166" Y="320" T="1678312446158" /><Point X="165" Y="320" T="1678312446158" /><Point X="164" Y="320" T="1678312446158" /><Point X="163" Y="321" T="1678312446158" /><Point X="161" Y="321" T="1678312446158" /><Point X="160" Y="323" T="1678312446158" /><Point X="159" Y="323" T="1678312446158" /><Point X="158" Y="323" T="1678312446158" /><Point X="157" Y="323" T="1678312446158" /><Point X="156" Y="323" T="1678312446158" /></Gesture>