<Gesture Name="star" Subject="1" Number="1" NumPts="139" Millseconds="0" AppName="Gestures" AppVer="1.0" Date="Thursday, March 02, 2023" TimeOfDay="13:33:08&#10;" ID="9"><Point X="145" Y="332" T="1677781988779" /><Point X="164" Y="300" T="1677781988779" /><Point X="178" Y="276" T="1677781988779" /><Point X="199" Y="242" T="1677781988779" /><Point X="210" Y="213" T="1677781988779" /><Point X="218" Y="198" T="1677781988779" /><Point X="222" Y="186" T="1677781988779" /><Point X="230" Y="167" T="1677781988779" /><Point X="235" Y="155" T="1677781988779" /><Point X="239" Y="147" T="1677781988779" /><Point X="241" Y="141" T="1677781988779" /><Point X="242" Y="138" T="1677781988779" /><Point X="244" Y="135" T="1677781988779" /><Point X="246" Y="134" T="1677781988779" /><Point X="247" Y="132" T="1677781988779" /><Point X="248" Y="131" T="1677781988779" /><Point X="249" Y="130" T="1677781988779" /><Point X="250" Y="129" T="1677781988779" /><Point X="252" Y="127" T="1677781988779" /><Point X="254" Y="127" T="1677781988779" /><Point X="255" Y="126" T="1677781988779" /><Point X="256" Y="124" T="1677781988779" /><Point X="257" Y="124" T="1677781988779" /><Point X="257" Y="123" T="1677781988779" /><Point X="258" Y="123" T="1677781988779" /><Point X="260" Y="123" T="1677781988779" /><Point X="261" Y="125" T="1677781988779" /><Point X="262" Y="131" T="1677781988779" /><Point X="265" Y="142" T="1677781988779" /><Point X="267" Y="152" T="1677781988779" /><Point X="270" Y="162" T="1677781988779" /><Point X="274" Y="177" T="1677781988779" /><Point X="276" Y="198" T="1677781988779" /><Point X="278" Y="211" T="1677781988779" /><Point X="283" Y="223" T="1677781988779" /><Point X="286" Y="232" T="1677781988779" /><Point X="293" Y="243" T="1677781988779" /><Point X="298" Y="255" T="1677781988779" /><Point X="305" Y="265" T="1677781988779" /><Point X="310" Y="274" T="1677781988779" /><Point X="314" Y="280" T="1677781988779" /><Point X="318" Y="286" T="1677781988779" /><Point X="322" Y="291" T="1677781988779" /><Point X="329" Y="297" T="1677781988779" /><Point X="332" Y="301" T="1677781988779" /><Point X="337" Y="306" T="1677781988779" /><Point X="341" Y="309" T="1677781988779" /><Point X="346" Y="313" T="1677781988779" /><Point X="348" Y="315" T="1677781988779" /><Point X="350" Y="318" T="1677781988779" /><Point X="352" Y="320" T="1677781988779" /><Point X="353" Y="320" T="1677781988779" /><Point X="354" Y="321" T="1677781988779" /><Point X="354" Y="322" T="1677781988779" /><Point X="354" Y="323" T="1677781988779" /><Point X="352" Y="323" T="1677781988779" /><Point X="349" Y="320" T="1677781988779" /><Point X="342" Y="314" T="1677781988779" /><Point X="330" Y="309" T="1677781988779" /><Point X="312" Y="299" T="1677781988779" /><Point X="294" Y="287" T="1677781988779" /><Point X="277" Y="277" T="1677781988779" /><Point X="247" Y="259" T="1677781988779" /><Point X="216" Y="244" T="1677781988779" /><Point X="198" Y="235" T="1677781988779" /><Point X="175" Y="225" T="1677781988779" /><Point X="153" Y="218" T="1677781988779" /><Point X="138" Y="211" T="1677781988779" /><Point X="129" Y="208" T="1677781988779" /><Point X="122" Y="206" T="1677781988779" /><Point X="117" Y="203" T="1677781988779" /><Point X="112" Y="203" T="1677781988779" /><Point X="110" Y="202" T="1677781988779" /><Point X="108" Y="202" T="1677781988779" /><Point X="106" Y="202" T="1677781988779" /><Point X="105" Y="202" T="1677781988779" /><Point X="104" Y="202" T="1677781988779" /><Point X="103" Y="202" T="1677781988779" /><Point X="104" Y="203" T="1677781988779" /><Point X="110" Y="204" T="1677781988779" /><Point X="122" Y="205" T="1677781988779" /><Point X="136" Y="205" T="1677781988779" /><Point X="149" Y="205" T="1677781988779" /><Point X="170" Y="205" T="1677781988779" /><Point X="194" Y="203" T="1677781988779" /><Point X="216" Y="199" T="1677781988779" /><Point X="242" Y="195" T="1677781988779" /><Point X="268" Y="190" T="1677781988779" /><Point X="293" Y="182" T="1677781988779" /><Point X="312" Y="178" T="1677781988779" /><Point X="335" Y="174" T="1677781988779" /><Point X="347" Y="171" T="1677781988779" /><Point X="357" Y="171" T="1677781988779" /><Point X="362" Y="171" T="1677781988779" /><Point X="369" Y="171" T="1677781988779" /><Point X="374" Y="172" T="1677781988779" /><Point X="379" Y="173" T="1677781988779" /><Point X="383" Y="175" T="1677781988779" /><Point X="386" Y="175" T="1677781988779" /><Point X="390" Y="175" T="1677781988781" /><Point X="393" Y="176" T="1677781988781" /><Point X="395" Y="177" T="1677781988781" /><Point X="396" Y="178" T="1677781988781" /><Point X="398" Y="178" T="1677781988781" /><Point X="399" Y="178" T="1677781988781" /><Point X="400" Y="179" T="1677781988781" /><Point X="400" Y="180" T="1677781988781" /><Point X="400" Y="181" T="1677781988781" /><Point X="400" Y="182" T="1677781988781" /><Point X="397" Y="182" T="1677781988781" /><Point X="394" Y="183" T="1677781988781" /><Point X="387" Y="185" T="1677781988781" /><Point X="374" Y="191" T="1677781988781" /><Point X="354" Y="197" T="1677781988781" /><Point X="331" Y="210" T="1677781988781" /><Point X="304" Y="228" T="1677781988781" /><Point X="269" Y="248" T="1677781988781" /><Point X="245" Y="263" T="1677781988781" /><Point X="223" Y="277" T="1677781988781" /><Point X="193" Y="300" T="1677781988781" /><Point X="170" Y="322" T="1677781988781" /><Point X="155" Y="335" T="1677781988781" /><Point X="142" Y="347" T="1677781988781" /><Point X="131" Y="355" T="1677781988781" /><Point X="122" Y="363" T="1677781988781" /><Point X="114" Y="371" T="1677781988781" /><Point X="107" Y="377" T="1677781988781" /><Point X="102" Y="382" T="1677781988781" /><Point X="99" Y="384" T="1677781988781" /><Point X="96" Y="386" T="1677781988781" /><Point X="94" Y="388" T="1677781988781" /><Point X="94" Y="389" T="1677781988781" /><Point X="93" Y="390" T="1677781988781" /><Point X="92" Y="391" T="1677781988781" /><Point X="91" Y="391" T="1677781988781" /><Point X="90" Y="392" T="1677781988781" /><Point X="89" Y="392" T="1677781988781" /><Point X="89" Y="394" T="1677781988781" /><Point X="88" Y="394" T="1677781988781" /></Gesture>