<Gesture Name="triangle" Subject="1" Number="1" NumPts="84" Millseconds="0" AppName="Gestures" AppVer="1.0" Date="Thursday, March 02, 2023" TimeOfDay="13:30:58&#10;" ID="7"><Point X="261" Y="144" T="1677781858585" /><Point X="245" Y="168" T="1677781858585" /><Point X="232" Y="190" T="1677781858585" /><Point X="225" Y="201" T="1677781858585" /><Point X="214" Y="215" T="1677781858585" /><Point X="199" Y="236" T="1677781858585" /><Point X="184" Y="256" T="1677781858585" /><Point X="176" Y="267" T="1677781858585" /><Point X="168" Y="276" T="1677781858585" /><Point X="163" Y="283" T="1677781858585" /><Point X="157" Y="291" T="1677781858585" /><Point X="149" Y="301" T="1677781858585" /><Point X="143" Y="309" T="1677781858585" /><Point X="138" Y="317" T="1677781858585" /><Point X="134" Y="323" T="1677781858585" /><Point X="129" Y="329" T="1677781858585" /><Point X="126" Y="332" T="1677781858585" /><Point X="125" Y="337" T="1677781858585" /><Point X="123" Y="342" T="1677781858585" /><Point X="120" Y="347" T="1677781858585" /><Point X="119" Y="351" T="1677781858585" /><Point X="118" Y="355" T="1677781858585" /><Point X="118" Y="357" T="1677781858585" /><Point X="118" Y="360" T="1677781858585" /><Point X="118" Y="361" T="1677781858585" /><Point X="121" Y="363" T="1677781858585" /><Point X="125" Y="363" T="1677781858585" /><Point X="131" Y="363" T="1677781858585" /><Point X="141" Y="363" T="1677781858585" /><Point X="153" Y="359" T="1677781858585" /><Point X="169" Y="354" T="1677781858585" /><Point X="181" Y="351" T="1677781858585" /><Point X="194" Y="348" T="1677781858585" /><Point X="216" Y="343" T="1677781858585" /><Point X="237" Y="340" T="1677781858585" /><Point X="254" Y="338" T="1677781858585" /><Point X="272" Y="335" T="1677781858585" /><Point X="294" Y="334" T="1677781858585" /><Point X="310" Y="331" T="1677781858585" /><Point X="323" Y="331" T="1677781858585" /><Point X="335" Y="331" T="1677781858585" /><Point X="345" Y="331" T="1677781858585" /><Point X="354" Y="331" T="1677781858585" /><Point X="362" Y="329" T="1677781858585" /><Point X="369" Y="329" T="1677781858585" /><Point X="373" Y="329" T="1677781858585" /><Point X="377" Y="329" T="1677781858585" /><Point X="380" Y="329" T="1677781858585" /><Point X="382" Y="329" T="1677781858585" /><Point X="386" Y="329" T="1677781858585" /><Point X="387" Y="329" T="1677781858585" /><Point X="388" Y="329" T="1677781858585" /><Point X="389" Y="328" T="1677781858585" /><Point X="389" Y="326" T="1677781858585" /><Point X="389" Y="321" T="1677781858585" /><Point X="387" Y="313" T="1677781858585" /><Point X="384" Y="303" T="1677781858585" /><Point X="379" Y="295" T="1677781858585" /><Point X="371" Y="283" T="1677781858585" /><Point X="357" Y="261" T="1677781858585" /><Point X="346" Y="244" T="1677781858585" /><Point X="338" Y="233" T="1677781858585" /><Point X="331" Y="223" T="1677781858585" /><Point X="324" Y="212" T="1677781858585" /><Point X="316" Y="201" T="1677781858585" /><Point X="310" Y="191" T="1677781858585" /><Point X="304" Y="183" T="1677781858585" /><Point X="300" Y="178" T="1677781858585" /><Point X="295" Y="173" T="1677781858585" /><Point X="292" Y="167" T="1677781858585" /><Point X="289" Y="161" T="1677781858585" /><Point X="286" Y="156" T="1677781858585" /><Point X="283" Y="151" T="1677781858585" /><Point X="282" Y="147" T="1677781858585" /><Point X="281" Y="143" T="1677781858585" /><Point X="280" Y="139" T="1677781858585" /><Point X="279" Y="136" T="1677781858585" /><Point X="278" Y="134" T="1677781858585" /><Point X="278" Y="132" T="1677781858585" /><Point X="277" Y="131" T="1677781858585" /><Point X="277" Y="129" T="1677781858585" /><Point X="277" Y="128" T="1677781858585" /><Point X="277" Y="127" T="1677781858585" /><Point X="276" Y="127" T="1677781858585" /></Gesture>