<Gesture Name="x" Subject="1" Number="1" NumPts="61" Millseconds="0" AppName="Gestures" AppVer="1.0" Date="Thursday, March 02, 2023" TimeOfDay="13:33:24&#10;" ID="10"><Point X="191" Y="158" T="1677782004421" /><Point X="202" Y="164" T="1677782004421" /><Point X="213" Y="174" T="1677782004421" /><Point X="225" Y="184" T="1677782004421" /><Point X="234" Y="195" T="1677782004421" /><Point X="243" Y="201" T="1677782004421" /><Point X="251" Y="208" T="1677782004421" /><Point X="257" Y="215" T="1677782004421" /><Point X="265" Y="221" T="1677782004421" /><Point X="274" Y="228" T="1677782004421" /><Point X="280" Y="236" T="1677782004421" /><Point X="287" Y="243" T="1677782004421" /><Point X="294" Y="249" T="1677782004421" /><Point X="299" Y="252" T="1677782004421" /><Point X="304" Y="258" T="1677782004421" /><Point X="306" Y="259" T="1677782004421" /><Point X="309" Y="262" T="1677782004421" /><Point X="311" Y="264" T="1677782004421" /><Point X="313" Y="266" T="1677782004421" /><Point X="314" Y="267" T="1677782004421" /><Point X="315" Y="268" T="1677782004421" /><Point X="315" Y="269" T="1677782004421" /><Point X="318" Y="266" T="1677782004421" /><Point X="320" Y="256" T="1677782004421" /><Point X="321" Y="247" T="1677782004421" /><Point X="321" Y="237" T="1677782004421" /><Point X="322" Y="223" T="1677782004421" /><Point X="323" Y="200" T="1677782004421" /><Point X="325" Y="186" T="1677782004421" /><Point X="325" Y="174" T="1677782004421" /><Point X="325" Y="160" T="1677782004421" /><Point X="325" Y="147" T="1677782004421" /><Point X="325" Y="140" T="1677782004421" /><Point X="325" Y="136" T="1677782004421" /><Point X="325" Y="135" T="1677782004421" /><Point X="325" Y="134" T="1677782004421" /><Point X="325" Y="133" T="1677782004421" /><Point X="324" Y="133" T="1677782004421" /><Point X="323" Y="135" T="1677782004421" /><Point X="320" Y="139" T="1677782004421" /><Point X="313" Y="146" T="1677782004421" /><Point X="301" Y="158" T="1677782004421" /><Point X="281" Y="181" T="1677782004421" /><Point X="265" Y="199" T="1677782004421" /><Point X="252" Y="211" T="1677782004421" /><Point X="229" Y="235" T="1677782004421" /><Point X="206" Y="265" T="1677782004421" /><Point X="193" Y="282" T="1677782004421" /><Point X="185" Y="292" T="1677782004421" /><Point X="179" Y="299" T="1677782004421" /><Point X="174" Y="306" T="1677782004421" /><Point X="168" Y="313" T="1677782004421" /><Point X="166" Y="318" T="1677782004421" /><Point X="162" Y="321" T="1677782004421" /><Point X="162" Y="323" T="1677782004421" /><Point X="161" Y="324" T="1677782004421" /><Point X="160" Y="324" T="1677782004421" /><Point X="159" Y="325" T="1677782004421" /><Point X="159" Y="326" T="1677782004421" /><Point X="158" Y="327" T="1677782004421" /><Point X="157" Y="327" T="1677782004421" /></Gesture>