<Gesture Name="d" Subject="1" Number="1" NumPts="182" Millseconds="0" AppName="Gestures" AppVer="1.0" Date="Monday, April 17, 2023" TimeOfDay="05:33:08&#10;" ID="10"><Point X="227" Y="341" T="1681734788907" /><Point X="229" Y="338" T="1681734788907" /><Point X="231" Y="335" T="1681734788907" /><Point X="232" Y="334" T="1681734788907" /><Point X="234" Y="332" T="1681734788907" /><Point X="236" Y="330" T="1681734788907" /><Point X="238" Y="329" T="1681734788907" /><Point X="240" Y="327" T="1681734788907" /><Point X="243" Y="326" T="1681734788907" /><Point X="245" Y="324" T="1681734788907" /><Point X="248" Y="322" T="1681734788907" /><Point X="251" Y="320" T="1681734788907" /><Point X="254" Y="318" T="1681734788907" /><Point X="257" Y="316" T="1681734788907" /><Point X="261" Y="314" T="1681734788907" /><Point X="264" Y="312" T="1681734788907" /><Point X="267" Y="310" T="1681734788907" /><Point X="268" Y="309" T="1681734788907" /><Point X="270" Y="308" T="1681734788907" /><Point X="272" Y="307" T="1681734788907" /><Point X="273" Y="306" T="1681734788907" /><Point X="274" Y="306" T="1681734788907" /><Point X="275" Y="306" T="1681734788907" /><Point X="275" Y="305" T="1681734788907" /><Point X="276" Y="305" T="1681734788907" /><Point X="276" Y="304" T="1681734788907" /><Point X="275" Y="304" T="1681734788907" /><Point X="273" Y="304" T="1681734788907" /><Point X="271" Y="305" T="1681734788907" /><Point X="268" Y="305" T="1681734788907" /><Point X="267" Y="306" T="1681734788907" /><Point X="265" Y="306" T="1681734788907" /><Point X="263" Y="308" T="1681734788907" /><Point X="261" Y="310" T="1681734788907" /><Point X="259" Y="311" T="1681734788907" /><Point X="257" Y="314" T="1681734788907" /><Point X="255" Y="316" T="1681734788907" /><Point X="253" Y="318" T="1681734788907" /><Point X="252" Y="321" T="1681734788907" /><Point X="249" Y="324" T="1681734788907" /><Point X="245" Y="328" T="1681734788907" /><Point X="243" Y="332" T="1681734788907" /><Point X="240" Y="336" T="1681734788907" /><Point X="238" Y="339" T="1681734788907" /><Point X="236" Y="342" T="1681734788907" /><Point X="235" Y="346" T="1681734788907" /><Point X="235" Y="350" T="1681734788907" /><Point X="235" Y="354" T="1681734788907" /><Point X="234" Y="359" T="1681734788907" /><Point X="234" Y="362" T="1681734788907" /><Point X="235" Y="365" T="1681734788907" /><Point X="235" Y="366" T="1681734788907" /><Point X="235" Y="368" T="1681734788907" /><Point X="236" Y="369" T="1681734788907" /><Point X="237" Y="370" T="1681734788907" /><Point X="239" Y="371" T="1681734788907" /><Point X="240" Y="373" T="1681734788907" /><Point X="241" Y="373" T="1681734788907" /><Point X="243" Y="374" T="1681734788907" /><Point X="244" Y="374" T="1681734788907" /><Point X="245" Y="374" T="1681734788907" /><Point X="246" Y="374" T="1681734788907" /><Point X="248" Y="374" T="1681734788907" /><Point X="249" Y="374" T="1681734788907" /><Point X="251" Y="373" T="1681734788907" /><Point X="252" Y="372" T="1681734788907" /><Point X="255" Y="371" T="1681734788907" /><Point X="258" Y="369" T="1681734788907" /><Point X="261" Y="366" T="1681734788907" /><Point X="264" Y="363" T="1681734788907" /><Point X="267" Y="360" T="1681734788907" /><Point X="268" Y="358" T="1681734788907" /><Point X="269" Y="356" T="1681734788907" /><Point X="270" Y="354" T="1681734788907" /><Point X="271" Y="352" T="1681734788907" /><Point X="273" Y="349" T="1681734788907" /><Point X="275" Y="345" T="1681734788907" /><Point X="276" Y="340" T="1681734788907" /><Point X="277" Y="336" T="1681734788907" /><Point X="277" Y="333" T="1681734788907" /><Point X="278" Y="330" T="1681734788907" /><Point X="279" Y="327" T="1681734788907" /><Point X="280" Y="323" T="1681734788907" /><Point X="281" Y="319" T="1681734788907" /><Point X="281" Y="316" T="1681734788907" /><Point X="282" Y="312" T="1681734788907" /><Point X="282" Y="309" T="1681734788907" /><Point X="282" Y="306" T="1681734788907" /><Point X="282" Y="303" T="1681734788907" /><Point X="283" Y="299" T="1681734788907" /><Point X="283" Y="294" T="1681734788907" /><Point X="284" Y="290" T="1681734788907" /><Point X="284" Y="286" T="1681734788907" /><Point X="284" Y="283" T="1681734788907" /><Point X="284" Y="281" T="1681734788907" /><Point X="284" Y="277" T="1681734788907" /><Point X="284" Y="274" T="1681734788907" /><Point X="285" Y="270" T="1681734788907" /><Point X="285" Y="266" T="1681734788907" /><Point X="285" Y="262" T="1681734788907" /><Point X="285" Y="259" T="1681734788907" /><Point X="284" Y="256" T="1681734788907" /><Point X="284" Y="253" T="1681734788907" /><Point X="284" Y="249" T="1681734788907" /><Point X="284" Y="243" T="1681734788907" /><Point X="284" Y="238" T="1681734788907" /><Point X="283" Y="235" T="1681734788907" /><Point X="283" Y="233" T="1681734788907" /><Point X="282" Y="230" T="1681734788907" /><Point X="282" Y="228" T="1681734788907" /><Point X="282" Y="226" T="1681734788907" /><Point X="281" Y="225" T="1681734788907" /><Point X="281" Y="223" T="1681734788907" /><Point X="280" Y="222" T="1681734788907" /><Point X="280" Y="220" T="1681734788907" /><Point X="280" Y="218" T="1681734788907" /><Point X="280" Y="217" T="1681734788907" /><Point X="280" Y="215" T="1681734788907" /><Point X="279" Y="213" T="1681734788907" /><Point X="279" Y="212" T="1681734788907" /><Point X="279" Y="211" T="1681734788907" /><Point X="278" Y="211" T="1681734788907" /><Point X="277" Y="211" T="1681734788907" /><Point X="276" Y="212" T="1681734788907" /><Point X="276" Y="213" T="1681734788907" /><Point X="275" Y="215" T="1681734788907" /><Point X="274" Y="217" T="1681734788907" /><Point X="273" Y="219" T="1681734788907" /><Point X="272" Y="223" T="1681734788907" /><Point X="272" Y="227" T="1681734788907" /><Point X="271" Y="232" T="1681734788907" /><Point X="271" Y="235" T="1681734788907" /><Point X="270" Y="238" T="1681734788907" /><Point X="271" Y="242" T="1681734788907" /><Point X="271" Y="247" T="1681734788907" /><Point X="272" Y="253" T="1681734788907" /><Point X="272" Y="258" T="1681734788907" /><Point X="273" Y="261" T="1681734788907" /><Point X="273" Y="265" T="1681734788907" /><Point X="274" Y="267" T="1681734788907" /><Point X="275" Y="271" T="1681734788907" /><Point X="276" Y="277" T="1681734788907" /><Point X="276" Y="282" T="1681734788907" /><Point X="276" Y="285" T="1681734788907" /><Point X="276" Y="289" T="1681734788907" /><Point X="276" Y="293" T="1681734788907" /><Point X="277" Y="297" T="1681734788907" /><Point X="278" Y="303" T="1681734788907" /><Point X="278" Y="307" T="1681734788907" /><Point X="278" Y="311" T="1681734788907" /><Point X="278" Y="314" T="1681734788907" /><Point X="279" Y="318" T="1681734788907" /><Point X="279" Y="322" T="1681734788907" /><Point X="280" Y="327" T="1681734788907" /><Point X="281" Y="332" T="1681734788907" /><Point X="281" Y="336" T="1681734788907" /><Point X="281" Y="339" T="1681734788907" /><Point X="282" Y="342" T="1681734788907" /><Point X="282" Y="346" T="1681734788907" /><Point X="283" Y="349" T="1681734788907" /><Point X="283" Y="353" T="1681734788907" /><Point X="284" Y="356" T="1681734788907" /><Point X="286" Y="359" T="1681734788907" /><Point X="288" Y="362" T="1681734788907" /><Point X="290" Y="365" T="1681734788907" /><Point X="292" Y="366" T="1681734788907" /><Point X="294" Y="368" T="1681734788907" /><Point X="296" Y="369" T="1681734788907" /><Point X="297" Y="370" T="1681734788907" /><Point X="299" Y="371" T="1681734788907" /><Point X="300" Y="372" T="1681734788907" /><Point X="302" Y="373" T="1681734788907" /><Point X="304" Y="373" T="1681734788907" /><Point X="307" Y="373" T="1681734788907" /><Point X="311" Y="373" T="1681734788907" /><Point X="313" Y="373" T="1681734788907" /><Point X="316" Y="373" T="1681734788907" /><Point X="318" Y="373" T="1681734788907" /><Point X="320" Y="373" T="1681734788907" /><Point X="321" Y="373" T="1681734788907" /><Point X="323" Y="373" T="1681734788907" /><Point X="324" Y="373" T="1681734788907" /></Gesture>