<Gesture Name="caret" Subject="1" Instance="1" NumPts="26" AppName="Gestures" Date="Wednesday, March 08, 2023" TimeOfDay="16:43:20" ID="3"><Point X="251" Y="572" T="1678311800575" /><Point X="252" Y="570" T="1678311800575" /><Point X="257" Y="564" T="1678311800575" /><Point X="264" Y="555" T="1678311800575" /><Point X="275" Y="544" T="1678311800575" /><Point X="283" Y="536" T="1678311800575" /><Point X="290" Y="529" T="1678311800575" /><Point X="296" Y="522" T="1678311800575" /><Point X="299" Y="518" T="1678311800575" /><Point X="302" Y="515" T="1678311800575" /><Point X="303" Y="513" T="1678311800575" /><Point X="304" Y="513" T="1678311800575" /><Point X="304" Y="514" T="1678311800575" /><Point X="305" Y="517" T="1678311800575" /><Point X="307" Y="525" T="1678311800575" /><Point X="310" Y="537" T="1678311800575" /><Point X="314" Y="551" T="1678311800575" /><Point X="318" Y="565" T="1678311800575" /><Point X="321" Y="576" T="1678311800575" /><Point X="324" Y="586" T="1678311800575" /><Point X="326" Y="593" T="1678311800575" /><Point X="328" Y="598" T="1678311800575" /><Point X="328" Y="601" T="1678311800575" /><Point X="329" Y="603" T="1678311800575" /><Point X="329" Y="604" T="1678311800575" /><Point X="329" Y="605" T="1678311800575" /></Gesture>